got/__init__.py
got/cli.py
got/commit.py
got/git.py
got/printer.py
got/ai/__init__.py
got/ai/chatgpt.py
got/ai/factory.py
got/ai/groq.py
got/prompts/default_examples.txt
got/prompts/default_prompt.txt
got/prompts/examples.txt
got/prompts/prompt.txt
got_cli-0.1.4.dist-info/LICENSE
got_cli-0.1.4.dist-info/METADATA
got_cli-0.1.4.dist-info/WHEEL
got_cli-0.1.4.dist-info/entry_points.txt
got_cli-0.1.4.dist-info/top_level.txt
got_cli-0.1.4.dist-info/RECORD
