Metadata-Version: 2.1
Name: got-cli
Version: 0.1.4
Summary: Got is a library to help you make consistent commit messages with help of AI
Home-page: https://github.com/GuiPimenta-Dev/got
Author: Guilherme Alves Pimenta
Author-email: guialvespimenta27@gmail.com
License: MIT
Platform: UNKNOWN
License-File: LICENSE
Requires-Dist: openai ==1.25.1
Requires-Dist: groq ==0.5.0
Requires-Dist: click ==8.1.3
Requires-Dist: python-dotenv ==1.0.1
Requires-Dist: blessed ==1.20.0
